exhaustion/__init__.py
exhaustion-1.0.3.dist-info/LICENSE
exhaustion-1.0.3.dist-info/WHEEL
exhaustion-1.0.3.dist-info/METADATA
exhaustion-1.0.3.dist-info/RECORD
