Metadata-Version: 2.1
Name: exhaustion
Version: 1.0.3
Summary: A tiny library to help in exhaustive testing of Boolean functions in Python.
Home-page: https://github.com/lambdacasserole/exhaustion.git
License: MIT
Author: Saul Johnson
Author-email: saul.a.johnson@gmail.com
Requires-Python: >=3.6,<4.0
Classifier: License :: OSI Approved :: MIT License
Classifier: Programming Language :: Python :: 3
Classifier: Programming Language :: Python :: 3.10
Classifier: Programming Language :: Python :: 3.6
Classifier: Programming Language :: Python :: 3.7
Classifier: Programming Language :: Python :: 3.8
Classifier: Programming Language :: Python :: 3.9
Project-URL: Repository, https://github.com/lambdacasserole/exhaustion.git
